README
setup.cfg
setup.py
sphinxcontrib/__init__.py
sphinxcontrib/dqndomain.py
sphinxcontrib_dqndomain.egg-info/PKG-INFO
sphinxcontrib_dqndomain.egg-info/SOURCES.txt
sphinxcontrib_dqndomain.egg-info/dependency_links.txt
sphinxcontrib_dqndomain.egg-info/namespace_packages.txt
sphinxcontrib_dqndomain.egg-info/not-zip-safe
sphinxcontrib_dqndomain.egg-info/requires.txt
sphinxcontrib_dqndomain.egg-info/top_level.txt