Metadata-Version: 1.1
Name: sphinxcontrib-dqndomain
Version: 0.1.0
Summary: Sphinx dqn extension
Home-page: https://bitbucket.org/takesxi_sximada/sphinxcontrib-dqndomain
Author: TakesxiSximada
Author-email: takesxi.sximada@gmail.com
License: BSD
Download-URL: https://bitbucket.org/takesxi_sximada/sphinxcontrib-dqndomain
Platform: any
Classifier: Development Status :: 3 - Alpha
Classifier: Environment :: Console
Classifier: Environment :: Web Environment
Classifier: Intended Audience :: Developers
Classifier: License :: OSI Approved :: BSD License
Classifier: Operating System :: OS Independent
Classifier: Programming Language :: Python
Classifier: Topic :: Documentation
Classifier: Topic :: Utilities
